bleprinter/__init__.py
bleprinter/ble.py
bleprinter/cmds.py
bleprinter/const.py
bleprinter/py.typed
bleprinter/text.py
bleprinter-0.2.0.dist-info/licenses/COPYING
bleprinter-0.2.0.dist-info/WHEEL
bleprinter-0.2.0.dist-info/METADATA
bleprinter-0.2.0.dist-info/RECORD
