Metadata-Version: 2.4
Name: bleprinter
Version: 0.2.0
Summary: A library for writing text to BLE receipt printers
Author: Benji
Author-email: Benji <figbert@figbert.com>
License-Expression: AGPL-3.0-or-later
License-File: COPYING
Requires-Dist: bleak>=1.0.1
Requires-Dist: opencv-python>=4.12.0.88
Requires-Python: >=3.13
